sctc/__init__.py
sctc/complexity_index.py
sctc/complexity_order.py
sctc/gene_space.py
sctc/ranking_plot.py
sctc-0.1.0.dist-info/LICENSE
sctc-0.1.0.dist-info/METADATA
sctc-0.1.0.dist-info/WHEEL
sctc-0.1.0.dist-info/top_level.txt
sctc-0.1.0.dist-info/RECORD
