Metadata-Version: 2.1
Name: sctc
Version: 0.1.0
Summary: Single-Cell Transcriptional Complexity (SCTC)
Author-email: Hai Lin <hailin@ucas.ac.cn>
Project-URL: Homepage, https://github.com/hailinphysics/sctc
Classifier: Programming Language :: Python :: 3
Classifier: License :: OSI Approved :: MIT License
Classifier: Operating System :: OS Independent
Requires-Python: >=3.6
License-File: LICENSE
